example_pkg/__init__.py
pceuropa_test-0.0.1.dist-info/LICENSE
pceuropa_test-0.0.1.dist-info/METADATA
pceuropa_test-0.0.1.dist-info/WHEEL
pceuropa_test-0.0.1.dist-info/top_level.txt
pceuropa_test-0.0.1.dist-info/RECORD
