Metadata-Version: 2.1
Name: pceuropa-test
Version: 0.0.1
Summary: Test utility package
Home-page: https://github.com/pceuropa/test
Author: Rafal Marguzewicz
Author-email: rafal@pceuropa.net
License: UNKNOWN
Platform: UNKNOWN
Classifier: Programming Language :: Python :: 3
Classifier: License :: OSI Approved :: MIT License
Classifier: Operating System :: OS Independent
